{"sections":{"page-header":{"type":"page-main-header","disabled":true,"settings":{"section_color_scheme":"general"}},"page-main":{"type":"page-main-content","settings":{}},"16563452958987f9f1":{"type":"flotilla-multi-collections","blocks":{"1656345295e276e922-1":{"type":"collection","settings":{"collection":"whats-new","heading":"{{ block.settings.collection.title }}","products_to_show":10,"button_style":"filled"}},"1656345295e276e922-0":{"type":"collection","settings":{"collection":"most-popular","heading":"{{ block.settings.collection.title }}","products_to_show":10,"button_style":"filled"}}},"block_order":["1656345295e276e922-1","1656345295e276e922-0"],"settings":{"subheading":"High-end streetwear marketplace","heading":"Spring\/summer ‘22","text_alignment":"center","visible_products":4,"section_color_scheme":"general"}},"16566911371b2dd201":{"type":"ship-callout-text","settings":{"section_width":"full-with-padding","horizontal_alignment":"text-center items-center","text":"CUSTOMERS from instagram","link_1":"","button_1_text":"","button_1_style":"fill","button_2_link":"","button_2_text":"","button_2_style":"outline","color_scheme":"general"}},"1656345300d576e925":{"type":"section-custom-liquid","settings":{"custom_liquid":"<div id=\"instaplus-feed-124731232\" class=\"instaplus-Shoppable\" data-gallerytype=\"InstaProductFeed\" data-id=\"124731232\"><\/div>","section_color_scheme":"general"}},"1656345388fe984a96":{"type":"section-collection-grid","blocks":{"1656345388701fed84-0":{"type":"collection","settings":{"collection":"womens-tops","collection_heading":"All Tops","vertical_text_alignment":"bottom","horizontal_text_alignment":"left","button_label":"","button_style":"filled","text_overlay_color_scheme":"accent-1","overlay_color_scheme":"bg-black","overlay_opacity":20}},"1656345388701fed84-1":{"type":"collection","settings":{"collection":"womens-bottoms","collection_heading":"All Bottoms","vertical_text_alignment":"bottom","horizontal_text_alignment":"left","button_label":"","button_style":"filled","text_overlay_color_scheme":"accent-1","overlay_color_scheme":"bg-black","overlay_opacity":20}},"1656345388701fed84-2":{"type":"collection","settings":{"collection":"accessories","collection_heading":"Accessories","vertical_text_alignment":"bottom","horizontal_text_alignment":"left","button_label":"","button_style":"filled","text_overlay_color_scheme":"accent-1","overlay_color_scheme":"bg-black","overlay_opacity":20}},"4e0cbc01-1fd1-4f94-b694-c85e4ab666bd":{"type":"collection","settings":{"collection":"shoes","collection_heading":"Shoes","vertical_text_alignment":"bottom","horizontal_text_alignment":"left","button_label":"","button_style":"filled","text_overlay_color_scheme":"accent-1","overlay_color_scheme":"bg-black","overlay_opacity":20}}},"block_order":["1656345388701fed84-0","1656345388701fed84-1","1656345388701fed84-2","4e0cbc01-1fd1-4f94-b694-c85e4ab666bd"],"settings":{"subheading":"","heading":"","text_alignment":"center","collections_per_row_desktop":4,"collections_per_row_mobile":"2","section_color_scheme":"general"}},"8e48661a-5a7a-4ab6-95c8-2a19574e859a":{"type":"flotilla-multi-collections","blocks":{"template--14479931801698__8e48661a-5a7a-4ab6-95c8-2a19574e859a-16668756828755b0c0-0":{"type":"collection","settings":{"collection":"on-sale","heading":"{{ block.settings.collection.title }}","products_to_show":10,"button_style":"filled"}},"template--14479931801698__8e48661a-5a7a-4ab6-95c8-2a19574e859a-16668756828755b0c0-1":{"type":"collection","disabled":true,"settings":{"collection":"","heading":"{{ block.settings.collection.title }}","products_to_show":8,"button_style":"filled"}},"template--14479931801698__8e48661a-5a7a-4ab6-95c8-2a19574e859a-16668756828755b0c0-2":{"type":"collection","disabled":true,"settings":{"collection":"","heading":"{{ block.settings.collection.title }}","products_to_show":8,"button_style":"filled"}}},"block_order":["template--14479931801698__8e48661a-5a7a-4ab6-95c8-2a19574e859a-16668756828755b0c0-0","template--14479931801698__8e48661a-5a7a-4ab6-95c8-2a19574e859a-16668756828755b0c0-1","template--14479931801698__8e48661a-5a7a-4ab6-95c8-2a19574e859a-16668756828755b0c0-2"],"settings":{"subheading":"","heading":"ON SALE","text_alignment":"center","visible_products":4,"section_color_scheme":"general"}},"165634547866eb99be":{"type":"section-featured-collection","disabled":true,"settings":{"collection":"on-sale","subheading":"Last chance to cop","heading":"On Sale","alignment":"text-left","products_per_page":8,"products_per_row":4,"products_per_row_mobile":"2","color_scheme":"general"}},"1656345992e520b3ac":{"type":"ship-callout-text","disabled":true,"settings":{"section_width":"narrow","horizontal_alignment":"text-center items-center","text":"","link_1":"shopify:\/\/collections\/on-sale","button_1_text":"View more","button_1_style":"fill","button_2_link":"","button_2_text":"","button_2_style":"outline","color_scheme":"general"}},"16566916457e59531a":{"type":"flotilla-image-with-text","disabled":true,"blocks":{"1656691644d858583b-0":{"type":"text","settings":{"subheading":"","heading":"Fuck the internet!","body_text":"New spring\/summer '22 collection by the emerging streetwear brand \"Fuck The Internet!\"","button_link":"shopify:\/\/collections\/fuck-the-internet","button_text":"Shop now","button_style":"outline"}},"1656691644d858583b-1":{"type":"text","disabled":true,"settings":{"subheading":"","heading":"Image with text","body_text":"Use text slides, paired with a large image to create a captivating brand story, explain details of your products, or even provide reviews.","button_link":"","button_text":"Shop now","button_style":"outline"}},"1656691644d858583b-2":{"type":"text","disabled":true,"settings":{"subheading":"","heading":"Image with text","body_text":"Use text slides, paired with a large image to create a captivating brand story, explain details of your products, or even provide reviews.","button_link":"","button_text":"Shop now","button_style":"outline"}}},"block_order":["1656691644d858583b-0","1656691644d858583b-1","1656691644d858583b-2"],"settings":{"image_position":"md:flex-row","image":"shopify:\/\/shop_images\/3E9E89EB-5134-4B96-BC05-C2882107C525.jpg","bg_color_scheme":"general","content_color_scheme":"accent-1"}},"1656691144e1c86f29":{"type":"section-featured-collection","disabled":true,"settings":{"collection":"unisex","subheading":"","heading":"Unisex","alignment":"text-left","products_per_page":8,"products_per_row":4,"products_per_row_mobile":"2","color_scheme":"general"}},"1656691189d0501b11":{"type":"ship-callout-text","disabled":true,"settings":{"section_width":"narrow","horizontal_alignment":"text-center items-center","text":"","link_1":"shopify:\/\/collections\/unisex","button_1_text":"View more","button_1_style":"fill","button_2_link":"","button_2_text":"","button_2_style":"outline","color_scheme":"general"}},"0ec1f633-c6c1-4c6c-994e-44e432c8a2a8":{"type":"flotilla-multi-collections","blocks":{"template--14479931801698__0ec1f633-c6c1-4c6c-994e-44e432c8a2a8-16668757783e278941-0":{"type":"collection","settings":{"collection":"unisex","heading":"{{ block.settings.collection.title }}","products_to_show":10,"button_style":"filled"}},"template--14479931801698__0ec1f633-c6c1-4c6c-994e-44e432c8a2a8-16668757783e278941-1":{"type":"collection","disabled":true,"settings":{"collection":"","heading":"{{ block.settings.collection.title }}","products_to_show":8,"button_style":"filled"}},"template--14479931801698__0ec1f633-c6c1-4c6c-994e-44e432c8a2a8-16668757783e278941-2":{"type":"collection","disabled":true,"settings":{"collection":"","heading":"{{ block.settings.collection.title }}","products_to_show":8,"button_style":"filled"}}},"block_order":["template--14479931801698__0ec1f633-c6c1-4c6c-994e-44e432c8a2a8-16668757783e278941-0","template--14479931801698__0ec1f633-c6c1-4c6c-994e-44e432c8a2a8-16668757783e278941-1","template--14479931801698__0ec1f633-c6c1-4c6c-994e-44e432c8a2a8-16668757783e278941-2"],"settings":{"subheading":"","heading":"UNISEX","text_alignment":"center","visible_products":4,"section_color_scheme":"general"}},"165642475391094f7d":{"type":"flotilla-collection-slideshow","blocks":{"165642475381e70737-0":{"type":"collection","settings":{"collection":"whats-new","collection_heading":"","vertical_text_alignment":"bottom","horizontal_text_alignment":"left","button_label":"Shop now","button_style":"filled","text_overlay_color_scheme":"accent-1","overlay_color_scheme":"bg-black","overlay_opacity":20}},"165642475381e70737-1":{"type":"collection","settings":{"collection":"most-popular","collection_heading":"","vertical_text_alignment":"bottom","horizontal_text_alignment":"left","button_label":"Shop now","button_style":"filled","text_overlay_color_scheme":"accent-1","overlay_color_scheme":"bg-black","overlay_opacity":20}},"165642475381e70737-2":{"type":"collection","disabled":true,"settings":{"collection":"","collection_heading":"","vertical_text_alignment":"bottom","horizontal_text_alignment":"left","button_label":"Shop now","button_style":"filled","text_overlay_color_scheme":"accent-1","overlay_color_scheme":"bg-black","overlay_opacity":20}},"165642475381e70737-3":{"type":"collection","disabled":true,"settings":{"collection":"","collection_heading":"","vertical_text_alignment":"bottom","horizontal_text_alignment":"left","button_label":"Shop now","button_style":"filled","text_overlay_color_scheme":"accent-1","overlay_color_scheme":"bg-black","overlay_opacity":20}}},"block_order":["165642475381e70737-0","165642475381e70737-1","165642475381e70737-2","165642475381e70737-3"],"settings":{"subheading":"","heading":"","text_alignment":"left","visible_collections_desktop":4,"visible_collections_mobile":"2","section_color_scheme":"general"}}},"order":["page-header","page-main","16563452958987f9f1","16566911371b2dd201","1656345300d576e925","1656345388fe984a96","8e48661a-5a7a-4ab6-95c8-2a19574e859a","165634547866eb99be","1656345992e520b3ac","16566916457e59531a","1656691144e1c86f29","1656691189d0501b11","0ec1f633-c6c1-4c6c-994e-44e432c8a2a8","165642475391094f7d"]}